{
  "stable": {
    "lb_fast": 20,
    "lb_slow": 60,
    "sma_filter": 120,
    "k": 1,
    "atr_mult": 3.2,
    "max_w_core": 0.6,
    "max_w_alt": 0.35,
    "vol_lb": 20,
    "target_vol": 0.35,
    "rebalance_every": 1,
    "regime_sma": 180,
    "risk_off_exposure": 0.05,
    "atr_period": 14,
    "fee": 0.001,
    "slip": 0.0005
  },
  "balanced": {
    "lb_fast": 20,
    "lb_slow": 60,
    "sma_filter": 100,
    "k": 1,
    "atr_mult": 2.8,
    "max_w_core": 0.6,
    "max_w_alt": 0.3,
    "vol_lb": 20,
    "target_vol": 0.35,
    "rebalance_every": 3,
    "regime_sma": 200,
    "risk_off_exposure": 0.4,
    "atr_period": 14,
    "fee": 0.001,
    "slip": 0.0005
  },
  "aggressive": {
    "lb_fast": 20,
    "lb_slow": 60,
    "sma_filter": 80,
    "k": 2,
    "atr_mult": 2.2,
    "max_w_core": 0.7,
    "max_w_alt": 0.4,
    "vol_lb": 20,
    "target_vol": 0.45,
    "rebalance_every": 1,
    "regime_sma": 200,
    "risk_off_exposure": 0.6,
    "atr_period": 14,
    "fee": 0.001,
    "slip": 0.0005
  },
  "stable_short_balanced": {
    "lb_fast": 20,
    "lb_slow": 60,
    "sma_filter": 120,
    "k": 1,
    "atr_mult": 3.2,
    "max_w_core": 0.6,
    "max_w_alt": 0.35,
    "vol_lb": 20,
    "target_vol": 0.28,
    "rebalance_every": 1,
    "regime_sma": 180,
    "risk_off_exposure": 0.1,
    "atr_period": 14,
    "fee": 0.001,
    "slip": 0.0005
  },
  "stable_shield": {
    "lb_fast": 20,
    "lb_slow": 60,
    "sma_filter": 140,
    "k": 1,
    "atr_mult": 3.8,
    "max_w_core": 0.6,
    "max_w_alt": 0.35,
    "vol_lb": 20,
    "target_vol": 0.24,
    "rebalance_every": 3,
    "regime_sma": 180,
    "risk_off_exposure": 0.05,
    "atr_period": 14,
    "fee": 0.001,
    "slip": 0.0005
  }
}
